censuspy/ase.py
censuspy/bds.py
censuspy/dcsf.py
censuspy-1.1.0.dist-info/DESCRIPTION.rst
censuspy-1.1.0.dist-info/METADATA
censuspy-1.1.0.dist-info/RECORD
censuspy-1.1.0.dist-info/WHEEL
censuspy-1.1.0.dist-info/metadata.json
censuspy-1.1.0.dist-info/top_level.txt
