Metadata-Version: 2.0
Name: censuspy
Version: 1.1.0
Summary: Lightweight wrapper to access gov data
Home-page: https://github.com/DnrkasEFF/censuspy
Author: Aadhi Manivannan
Author-email: dnrkaseff360@gmail.com
License: MIT
Download-URL: https://github.com/DnrkasEFF/censuspy/archive/1.1.0.tar.gz
Keywords: census,python,wrapper
Platform: UNKNOWN
Requires-Python: >=3
Requires-Dist: requests
